AUTHORS.rst
CONTRIBUTING.rst
HISTORY.rst
LICENSE
MANIFEST.in
README.md
setup.cfg
setup.py
docs/Makefile
docs/authors.rst
docs/conf.py
docs/contributing.rst
docs/history.rst
docs/index.rst
docs/installation.rst
docs/make.bat
docs/readme.rst
docs/usage.rst
docs/screenshots/001.first_run.png
docs/screenshots/002.diff_json.png
lazy_regression_tests/__init__.py
lazy_regression_tests/_baseutils.py
lazy_regression_tests/common.py
lazy_regression_tests/core.py
lazy_regression_tests/core_assist.py
lazy_regression_tests/filters.py
lazy_regression_tests/helper_tst.py
lazy_regression_tests/http_validators.py
lazy_regression_tests/json_schema_validators.py
lazy_regression_tests/utils.py
lazy_regression_tests/validators.py
lazy_regression_tests/yaml_validators.py
lazy_regression_tests.egg-info/PKG-INFO
lazy_regression_tests.egg-info/SOURCES.txt
lazy_regression_tests.egg-info/dependency_links.txt
lazy_regression_tests.egg-info/not-zip-safe
lazy_regression_tests.egg-info/requires.txt
lazy_regression_tests.egg-info/top_level.txt
tests/.coverage
tests/__init__.py
tests/test_core.py
tests/test_doc.py
tests/test_http.py
tests/test_jsonschema.py
tests/test_usage.py