Metadata-Version: 2.1
Name: lazy-regression-tests
Version: 0.5.4
Summary: Easier automatic validation and regression testing
Home-page: https://github.com/jpeyret/lazy-regression-tests
Author: JL Peyret
Author-email: jpeyret@gmail.com
License: MIT license
Keywords: lazy_regression_tests
Platform: UNKNOWN
Classifier: Development Status :: 4 - Beta
Classifier: Intended Audience :: Developers
Classifier: License :: OSI Approved :: MIT License
Classifier: Natural Language :: English
Classifier: Programming Language :: Python :: 3
Classifier: Programming Language :: Python :: 3.6
Classifier: Programming Language :: Python :: 3.7
Classifier: Programming Language :: Python :: 3.8
Requires-Python: >=3.6
